setup.py
tim/__init__.py
tim/timscript.py
tim_timetracker.egg-info/PKG-INFO
tim_timetracker.egg-info/SOURCES.txt
tim_timetracker.egg-info/dependency_links.txt
tim_timetracker.egg-info/entry_points.txt
tim_timetracker.egg-info/requires.txt
tim_timetracker.egg-info/top_level.txt