Metadata-Version: 1.1
Name: tim-timetracker
Version: 0.5.2
Summary: command line time logger with hledger backend for number crunching
Home-page: https://github.com/MatthiasKauer/tim
Author: Matthias Kauer
Author-email: mk.software@zuez.org
License: MIT
Platform: Any
Classifier: Development Status :: 4 - Beta
Classifier: Environment :: Console
Classifier: Intended Audience :: End Users/Desktop
Classifier: License :: OSI Approved :: MIT License
Classifier: Operating System :: OS Independent
Classifier: Programming Language :: Python
